<?xml version="1.0" encoding="UTF-8" standalone="yes"?>
<?mso-application progid="Word.Document"?>
<w:wordDocument xmlns:w="http://schemas.microsoft.com/office/word/2003/wordml" xmlns:v="urn:schemas-microsoft-com:vml" xmlns:w10="urn:schemas-microsoft-com:office:word" xmlns:sl="http://schemas.microsoft.com/schemaLibrary/2003/core" xmlns:aml="http://schemas.microsoft.com/aml/2001/core" xmlns:wx="http://schemas.microsoft.com/office/word/2003/auxHint" xmlns:o="urn:schemas-microsoft-com:office:office" xmlns:dt="uuid:C2F41010-65B3-11d1-A29F-00AA00C14882" w:macrosPresent="no" w:embeddedObjPresent="no" w:ocxPresent="no" xml:space="preserve"><o:DocumentProperties><o:Title>Simplified DocBook Article Title</o:Title><o:Author>*</o:Author><o:LastAuthor>*</o:LastAuthor><o:Revision>1</o:Revision><o:TotalTime>0</o:TotalTime><o:Created>2009-09-10T06:04:00Z</o:Created><o:LastSaved>2009-09-10T06:05:00Z</o:LastSaved><o:Pages>1</o:Pages><o:Words>27</o:Words><o:Characters>174</o:Characters><o:Company>XML Workshop</o:Company><o:Bytes>87552</o:Bytes><o:Lines>1</o:Lines><o:Paragraphs>1</o:Paragraphs><o:CharactersWithSpaces>200</o:CharactersWithSpaces><o:Version>11.6359</o:Version></o:DocumentProperties><o:CustomDocumentProperties><o:yawcConfigFile dt:dt="string">yawcSDocBook.ini</o:yawcConfigFile><o:DC.Type.scheme dt:dt="string"> </o:DC.Type.scheme><o:yawcHTMLTemplate dt:dt="string"> </o:yawcHTMLTemplate><o:yawcHTMLLevel dt:dt="string">0</o:yawcHTMLLevel></o:CustomDocumentProperties><w:fonts><w:defaultFonts w:ascii="Times New Roman" w:fareast="Times New Roman" w:h-ansi="Times New Roman" w:cs="Times New Roman"/><w:font w:name="Wingdings"><w:panose-1 w:val="05000000000000000000"/><w:charset w:val="02"/><w:family w:val="Auto"/><w:pitch w:val="variable"/><w:sig w:usb-0="00000000" w:usb-1="10000000" w:usb-2="00000000" w:usb-3="00000000" w:csb-0="80000000" w:csb-1="00000000"/></w:font><w:font w:name="Garamond"><w:panose-1 w:val="02020404030301010803"/><w:charset w:val="00"/><w:family w:val="Roman"/><w:pitch w:val="variable"/><w:sig w:usb-0="00000287" w:usb-1="00000000" w:usb-2="00000000" w:usb-3="00000000" w:csb-0="0000009F" w:csb-1="00000000"/></w:font></w:fonts><w:lists><w:listDef w:listDefId="0"><w:lsid w:val="FFFFFF7C"/><w:plt w:val="SingleLevel"/><w:tmpl w:val="2AFA196A"/><w:lvl w:ilvl="0"><w:start w:val="1"/><w:lvlText w:val="%1."/><w:lvlJc w:val="left"/><w:pPr><w:tabs><w:tab w:val="list" w:pos="1492"/></w:tabs><w:ind w:left="1492" w:hanging="360"/></w:pPr></w:lvl></w:listDef><w:listDef w:listDefId="1"><w:lsid w:val="FFFFFF7D"/><w:plt w:val="SingleLevel"/><w:tmpl w:val="144CF38E"/><w:lvl w:ilvl="0"><w:start w:val="1"/><w:lvlText w:val="%1."/><w:lvlJc w:val="left"/><w:pPr><w:tabs><w:tab w:val="list" w:pos="1209"/></w:tabs><w:ind w:left="1209" w:hanging="360"/></w:pPr></w:lvl></w:listDef><w:listDef w:listDefId="2"><w:lsid w:val="FFFFFF7E"/><w:plt w:val="SingleLevel"/><w:tmpl w:val="C8A03DB4"/><w:lvl w:ilvl="0"><w:start w:val="1"/><w:pStyle w:val="Listennummer3"/><w:lvlText w:val="%1."/><w:lvlJc w:val="left"/><w:pPr><w:tabs><w:tab w:val="list" w:pos="926"/></w:tabs><w:ind w:left="926" w:hanging="360"/></w:pPr></w:lvl></w:listDef><w:listDef w:listDefId="3"><w:lsid w:val="FFFFFF80"/><w:plt w:val="SingleLevel"/><w:tmpl w:val="6A86183A"/><w:lvl w:ilvl="0"><w:start w:val="1"/><w:nfc w:val="23"/><w:lvlText w:val=""/><w:lvlJc w:val="left"/><w:pPr><w:tabs><w:tab w:val="list" w:pos="1492"/></w:tabs><w:ind w:left="1492" w:hanging="360"/></w:pPr><w:rPr><w:rFonts w:ascii="Symbol" w:h-ansi="Symbol" w:hint="default"/></w:rPr></w:lvl></w:listDef><w:listDef w:listDefId="4"><w:lsid w:val="FFFFFF81"/><w:plt w:val="SingleLevel"/><w:tmpl w:val="90CE98AC"/><w:lvl w:ilvl="0"><w:start w:val="1"/><w:nfc w:val="23"/><w:lvlText w:val=""/><w:lvlJc w:val="left"/><w:pPr><w:tabs><w:tab w:val="list" w:pos="1209"/></w:tabs><w:ind w:left="1209" w:hanging="360"/></w:pPr><w:rPr><w:rFonts w:ascii="Symbol" w:h-ansi="Symbol" w:hint="default"/></w:rPr></w:lvl></w:listDef><w:listDef w:listDefId="5"><w:lsid w:val="FFFFFF82"/><w:plt w:val="SingleLevel"/><w:tmpl w:val="8996E46A"/><w:lvl w:ilvl="0"><w:start w:val="1"/><w:nfc w:val="23"/><w:lvlText w:val=""/><w:lvlJc w:val="left"/><w:pPr><w:tabs><w:tab w:val="list" w:pos="926"/></w:tabs><w:ind w:left="926" w:hanging="360"/></w:pPr><w:rPr><w:rFonts w:ascii="Symbol" w:h-ansi="Symbol" w:hint="default"/></w:rPr></w:lvl></w:listDef><w:listDef w:listDefId="6"><w:lsid w:val="FFFFFF83"/><w:plt w:val="SingleLevel"/><w:tmpl w:val="EC1C7A62"/><w:lvl w:ilvl="0"><w:start w:val="1"/><w:nfc w:val="23"/><w:pStyle w:val="Aufzhlungszeichen2"/><w:lvlText w:val="●"/><w:lvlJc w:val="left"/><w:pPr><w:tabs><w:tab w:val="list" w:pos="643"/></w:tabs><w:ind w:left="643" w:hanging="360"/></w:pPr><w:rPr><w:rFonts w:ascii="Times New Roman" w:h-ansi="Times New Roman" w:hint="default"/><w:sz w:val="20"/></w:rPr></w:lvl></w:listDef><w:listDef w:listDefId="7"><w:lsid w:val="07A31D7F"/><w:plt w:val="SingleLevel"/><w:tmpl w:val="A9D4BD36"/><w:lvl w:ilvl="0"><w:start w:val="1"/><w:nfc w:val="23"/><w:pStyle w:val="Aufzhlungszeichen3"/><w:lvlText w:val="●"/><w:lvlJc w:val="left"/><w:pPr><w:tabs><w:tab w:val="list" w:pos="936"/></w:tabs><w:ind w:left="360" w:first-line="216"/></w:pPr><w:rPr><w:rFonts w:ascii="Times New Roman" w:h-ansi="Times New Roman" w:hint="default"/><w:sz w:val="16"/></w:rPr></w:lvl></w:listDef><w:listDef w:listDefId="8"><w:lsid w:val="1BC46773"/><w:plt w:val="HybridMultilevel"/><w:tmpl w:val="FCBC4A18"/><w:lvl w:ilvl="0"><w:start w:val="1"/><w:pStyle w:val="Orgname"/><w:lvlText w:val="%1."/><w:lvlJc w:val="left"/><w:pPr><w:tabs><w:tab w:val="list" w:pos="720"/></w:tabs><w:ind w:left="720" w:hanging="360"/></w:pPr><w:rPr><w:rFonts w:hint="default"/></w:rPr></w:lvl><w:lvl w:ilvl="1" w:tentative="on"><w:start w:val="1"/><w:nfc w:val="4"/><w:lvlText w:val="%2."/><w:lvlJc w:val="left"/><w:pPr><w:tabs><w:tab w:val="list" w:pos="1440"/></w:tabs><w:ind w:left="1440" w:hanging="360"/></w:pPr></w:lvl><w:lvl w:ilvl="2" w:tentative="on"><w:start w:val="1"/><w:nfc w:val="2"/><w:lvlText w:val="%3."/><w:lvlJc w:val="right"/><w:pPr><w:tabs><w:tab w:val="list" w:pos="2160"/></w:tabs><w:ind w:left="2160" w:hanging="180"/></w:pPr></w:lvl><w:lvl w:ilvl="3" w:tentative="on"><w:start w:val="1"/><w:lvlText w:val="%4."/><w:lvlJc w:val="left"/><w:pPr><w:tabs><w:tab w:val="list" w:pos="2880"/></w:tabs><w:ind w:left="2880" w:hanging="360"/></w:pPr></w:lvl><w:lvl w:ilvl="4" w:tentative="on"><w:start w:val="1"/><w:nfc w:val="4"/><w:lvlText w:val="%5."/><w:lvlJc w:val="left"/><w:pPr><w:tabs><w:tab w:val="list" w:pos="3600"/></w:tabs><w:ind w:left="3600" w:hanging="360"/></w:pPr></w:lvl><w:lvl w:ilvl="5" w:tentative="on"><w:start w:val="1"/><w:nfc w:val="2"/><w:lvlText w:val="%6."/><w:lvlJc w:val="right"/><w:pPr><w:tabs><w:tab w:val="list" w:pos="4320"/></w:tabs><w:ind w:left="4320" w:hanging="180"/></w:pPr></w:lvl><w:lvl w:ilvl="6" w:tentative="on"><w:start w:val="1"/><w:lvlText w:val="%7."/><w:lvlJc w:val="left"/><w:pPr><w:tabs><w:tab w:val="list" w:pos="5040"/></w:tabs><w:ind w:left="5040" w:hanging="360"/></w:pPr></w:lvl><w:lvl w:ilvl="7" w:tentative="on"><w:start w:val="1"/><w:nfc w:val="4"/><w:lvlText w:val="%8."/><w:lvlJc w:val="left"/><w:pPr><w:tabs><w:tab w:val="list" w:pos="5760"/></w:tabs><w:ind w:left="5760" w:hanging="360"/></w:pPr></w:lvl><w:lvl w:ilvl="8" w:tentative="on"><w:start w:val="1"/><w:nfc w:val="2"/><w:lvlText w:val="%9."/><w:lvlJc w:val="right"/><w:pPr><w:tabs><w:tab w:val="list" w:pos="6480"/></w:tabs><w:ind w:left="6480" w:hanging="180"/></w:pPr></w:lvl></w:listDef><w:listDef w:listDefId="9"><w:lsid w:val="5C9E760F"/><w:plt w:val="HybridMultilevel"/><w:tmpl w:val="EAF6662A"/><w:lvl w:ilvl="0"><w:start w:val="1"/><w:nfc w:val="23"/><w:lvlText w:val=""/><w:lvlJc w:val="left"/><w:pPr><w:tabs><w:tab w:val="list" w:pos="1080"/></w:tabs><w:ind w:left="1080" w:hanging="360"/></w:pPr><w:rPr><w:rFonts w:ascii="Wingdings" w:h-ansi="Wingdings" w:hint="default"/></w:rPr></w:lvl><w:lvl w:ilvl="1" w:tentative="on"><w:start w:val="1"/><w:nfc w:val="23"/><w:lvlText w:val="o"/><w:lvlJc w:val="left"/><w:pPr><w:tabs><w:tab w:val="list" w:pos="1800"/></w:tabs><w:ind w:left="1800" w:hanging="360"/></w:pPr><w:rPr><w:rFonts w:ascii="Courier New" w:h-ansi="Courier New" w:hint="default"/></w:rPr></w:lvl><w:lvl w:ilvl="2" w:tentative="on"><w:start w:val="1"/><w:nfc w:val="23"/><w:lvlText w:val=""/><w:lvlJc w:val="left"/><w:pPr><w:tabs><w:tab w:val="list" w:pos="2520"/></w:tabs><w:ind w:left="2520" w:hanging="360"/></w:pPr><w:rPr><w:rFonts w:ascii="Wingdings" w:h-ansi="Wingdings" w:hint="default"/></w:rPr></w:lvl><w:lvl w:ilvl="3" w:tentative="on"><w:start w:val="1"/><w:nfc w:val="23"/><w:lvlText w:val=""/><w:lvlJc w:val="left"/><w:pPr><w:tabs><w:tab w:val="list" w:pos="3240"/></w:tabs><w:ind w:left="3240" w:hanging="360"/></w:pPr><w:rPr><w:rFonts w:ascii="Symbol" w:h-ansi="Symbol" w:hint="default"/></w:rPr></w:lvl><w:lvl w:ilvl="4" w:tentative="on"><w:start w:val="1"/><w:nfc w:val="23"/><w:lvlText w:val="o"/><w:lvlJc w:val="left"/><w:pPr><w:tabs><w:tab w:val="list" w:pos="3960"/></w:tabs><w:ind w:left="3960" w:hanging="360"/></w:pPr><w:rPr><w:rFonts w:ascii="Courier New" w:h-ansi="Courier New" w:hint="default"/></w:rPr></w:lvl><w:lvl w:ilvl="5" w:tentative="on"><w:start w:val="1"/><w:nfc w:val="23"/><w:lvlText w:val=""/><w:lvlJc w:val="left"/><w:pPr><w:tabs><w:tab w:val="list" w:pos="4680"/></w:tabs><w:ind w:left="4680" w:hanging="360"/></w:pPr><w:rPr><w:rFonts w:ascii="Wingdings" w:h-ansi="Wingdings" w:hint="default"/></w:rPr></w:lvl><w:lvl w:ilvl="6" w:tentative="on"><w:start w:val="1"/><w:nfc w:val="23"/><w:lvlText w:val=""/><w:lvlJc w:val="left"/><w:pPr><w:tabs><w:tab w:val="list" w:pos="5400"/></w:tabs><w:ind w:left="5400" w:hanging="360"/></w:pPr><w:rPr><w:rFonts w:ascii="Symbol" w:h-ansi="Symbol" w:hint="default"/></w:rPr></w:lvl><w:lvl w:ilvl="7" w:tentative="on"><w:start w:val="1"/><w:nfc w:val="23"/><w:lvlText w:val="o"/><w:lvlJc w:val="left"/><w:pPr><w:tabs><w:tab w:val="list" w:pos="6120"/></w:tabs><w:ind w:left="6120" w:hanging="360"/></w:pPr><w:rPr><w:rFonts w:ascii="Courier New" w:h-ansi="Courier New" w:hint="default"/></w:rPr></w:lvl><w:lvl w:ilvl="8" w:tentative="on"><w:start w:val="1"/><w:nfc w:val="23"/><w:lvlText w:val=""/><w:lvlJc w:val="left"/><w:pPr><w:tabs><w:tab w:val="list" w:pos="6840"/></w:tabs><w:ind w:left="6840" w:hanging="360"/></w:pPr><w:rPr><w:rFonts w:ascii="Wingdings" w:h-ansi="Wingdings" w:hint="default"/></w:rPr></w:lvl></w:listDef><w:listDef w:listDefId="10"><w:lsid w:val="636B465B"/><w:plt w:val="SingleLevel"/><w:tmpl w:val="3702AD7A"/><w:lvl w:ilvl="0"><w:start w:val="1"/><w:nfc w:val="23"/><w:pStyle w:val="Aufzhlungszeichen"/><w:lvlText w:val="●"/><w:lvlJc w:val="left"/><w:pPr><w:tabs><w:tab w:val="list" w:pos="360"/></w:tabs><w:ind w:left="360" w:hanging="360"/></w:pPr><w:rPr><w:rFonts w:ascii="Times New Roman" w:h-ansi="Times New Roman" w:hint="default"/><w:sz w:val="24"/></w:rPr></w:lvl></w:listDef><w:listDef w:listDefId="11"><w:lsid w:val="63E51A16"/><w:plt w:val="SingleLevel"/><w:tmpl w:val="07B4FABE"/><w:lvl w:ilvl="0"><w:start w:val="1"/><w:nfc w:val="255"/><w:lvlText w:val=""/><w:legacy w:legacy="on" w:legacySpace="0" w:legacyIndent="360"/><w:lvlJc w:val="left"/><w:pPr><w:ind w:left="360" w:hanging="360"/></w:pPr></w:lvl></w:listDef><w:listDef w:listDefId="12"><w:lsid w:val="65414B16"/><w:plt w:val="HybridMultilevel"/><w:tmpl w:val="8BE2C35E"/><w:lvl w:ilvl="0"><w:start w:val="1"/><w:nfc w:val="23"/><w:pStyle w:val="Keywordset"/><w:lvlText w:val=""/><w:lvlJc w:val="left"/><w:pPr><w:tabs><w:tab w:val="list" w:pos="720"/></w:tabs><w:ind w:left="720" w:hanging="360"/></w:pPr><w:rPr><w:rFonts w:ascii="Symbol" w:h-ansi="Symbol" w:hint="default"/></w:rPr></w:lvl><w:lvl w:ilvl="1" w:tentative="on"><w:start w:val="1"/><w:nfc w:val="23"/><w:lvlText w:val="o"/><w:lvlJc w:val="left"/><w:pPr><w:tabs><w:tab w:val="list" w:pos="1440"/></w:tabs><w:ind w:left="1440" w:hanging="360"/></w:pPr><w:rPr><w:rFonts w:ascii="Courier New" w:h-ansi="Courier New" w:hint="default"/></w:rPr></w:lvl><w:lvl w:ilvl="2" w:tentative="on"><w:start w:val="1"/><w:nfc w:val="23"/><w:lvlText w:val=""/><w:lvlJc w:val="left"/><w:pPr><w:tabs><w:tab w:val="list" w:pos="2160"/></w:tabs><w:ind w:left="2160" w:hanging="360"/></w:pPr><w:rPr><w:rFonts w:ascii="Wingdings" w:h-ansi="Wingdings" w:hint="default"/></w:rPr></w:lvl><w:lvl w:ilvl="3" w:tentative="on"><w:start w:val="1"/><w:nfc w:val="23"/><w:lvlText w:val=""/><w:lvlJc w:val="left"/><w:pPr><w:tabs><w:tab w:val="list" w:pos="2880"/></w:tabs><w:ind w:left="2880" w:hanging="360"/></w:pPr><w:rPr><w:rFonts w:ascii="Symbol" w:h-ansi="Symbol" w:hint="default"/></w:rPr></w:lvl><w:lvl w:ilvl="4" w:tentative="on"><w:start w:val="1"/><w:nfc w:val="23"/><w:lvlText w:val="o"/><w:lvlJc w:val="left"/><w:pPr><w:tabs><w:tab w:val="list" w:pos="3600"/></w:tabs><w:ind w:left="3600" w:hanging="360"/></w:pPr><w:rPr><w:rFonts w:ascii="Courier New" w:h-ansi="Courier New" w:hint="default"/></w:rPr></w:lvl><w:lvl w:ilvl="5" w:tentative="on"><w:start w:val="1"/><w:nfc w:val="23"/><w:lvlText w:val=""/><w:lvlJc w:val="left"/><w:pPr><w:tabs><w:tab w:val="list" w:pos="4320"/></w:tabs><w:ind w:left="4320" w:hanging="360"/></w:pPr><w:rPr><w:rFonts w:ascii="Wingdings" w:h-ansi="Wingdings" w:hint="default"/></w:rPr></w:lvl><w:lvl w:ilvl="6" w:tentative="on"><w:start w:val="1"/><w:nfc w:val="23"/><w:lvlText w:val=""/><w:lvlJc w:val="left"/><w:pPr><w:tabs><w:tab w:val="list" w:pos="5040"/></w:tabs><w:ind w:left="5040" w:hanging="360"/></w:pPr><w:rPr><w:rFonts w:ascii="Symbol" w:h-ansi="Symbol" w:hint="default"/></w:rPr></w:lvl><w:lvl w:ilvl="7" w:tentative="on"><w:start w:val="1"/><w:nfc w:val="23"/><w:lvlText w:val="o"/><w:lvlJc w:val="left"/><w:pPr><w:tabs><w:tab w:val="list" w:pos="5760"/></w:tabs><w:ind w:left="5760" w:hanging="360"/></w:pPr><w:rPr><w:rFonts w:ascii="Courier New" w:h-ansi="Courier New" w:hint="default"/></w:rPr></w:lvl><w:lvl w:ilvl="8" w:tentative="on"><w:start w:val="1"/><w:nfc w:val="23"/><w:lvlText w:val=""/><w:lvlJc w:val="left"/><w:pPr><w:tabs><w:tab w:val="list" w:pos="6480"/></w:tabs><w:ind w:left="6480" w:hanging="360"/></w:pPr><w:rPr><w:rFonts w:ascii="Wingdings" w:h-ansi="Wingdings" w:hint="default"/></w:rPr></w:lvl></w:listDef><w:listDef w:listDefId="13"><w:lsid w:val="6FEC0FBD"/><w:plt w:val="SingleLevel"/><w:tmpl w:val="07B4FABE"/><w:lvl w:ilvl="0"><w:start w:val="1"/><w:nfc w:val="255"/><w:lvlText w:val=""/><w:legacy w:legacy="on" w:legacySpace="0" w:legacyIndent="360"/><w:lvlJc w:val="left"/><w:pPr><w:ind w:left="360" w:hanging="360"/></w:pPr></w:lvl></w:listDef><w:listDef w:listDefId="14"><w:lsid w:val="74C15CD7"/><w:plt w:val="HybridMultilevel"/><w:tmpl w:val="BDA2827C"/><w:lvl w:ilvl="0"><w:start w:val="1"/><w:nfc w:val="4"/><w:pStyle w:val="Listenfortsetzung5"/><w:lvlText w:val="%1."/><w:lvlJc w:val="left"/><w:pPr><w:tabs><w:tab w:val="list" w:pos="1080"/></w:tabs><w:ind w:left="1080" w:hanging="360"/></w:pPr><w:rPr><w:rFonts w:hint="default"/></w:rPr></w:lvl><w:lvl w:ilvl="1" w:tentative="on"><w:start w:val="1"/><w:nfc w:val="4"/><w:lvlText w:val="%2."/><w:lvlJc w:val="left"/><w:pPr><w:tabs><w:tab w:val="list" w:pos="1440"/></w:tabs><w:ind w:left="1440" w:hanging="360"/></w:pPr></w:lvl><w:lvl w:ilvl="2" w:tentative="on"><w:start w:val="1"/><w:nfc w:val="2"/><w:lvlText w:val="%3."/><w:lvlJc w:val="right"/><w:pPr><w:tabs><w:tab w:val="list" w:pos="2160"/></w:tabs><w:ind w:left="2160" w:hanging="180"/></w:pPr></w:lvl><w:lvl w:ilvl="3" w:tentative="on"><w:start w:val="1"/><w:lvlText w:val="%4."/><w:lvlJc w:val="left"/><w:pPr><w:tabs><w:tab w:val="list" w:pos="2880"/></w:tabs><w:ind w:left="2880" w:hanging="360"/></w:pPr></w:lvl><w:lvl w:ilvl="4" w:tentative="on"><w:start w:val="1"/><w:nfc w:val="4"/><w:lvlText w:val="%5."/><w:lvlJc w:val="left"/><w:pPr><w:tabs><w:tab w:val="list" w:pos="3600"/></w:tabs><w:ind w:left="3600" w:hanging="360"/></w:pPr></w:lvl><w:lvl w:ilvl="5" w:tentative="on"><w:start w:val="1"/><w:nfc w:val="2"/><w:lvlText w:val="%6."/><w:lvlJc w:val="right"/><w:pPr><w:tabs><w:tab w:val="list" w:pos="4320"/></w:tabs><w:ind w:left="4320" w:hanging="180"/></w:pPr></w:lvl><w:lvl w:ilvl="6" w:tentative="on"><w:start w:val="1"/><w:lvlText w:val="%7."/><w:lvlJc w:val="left"/><w:pPr><w:tabs><w:tab w:val="list" w:pos="5040"/></w:tabs><w:ind w:left="5040" w:hanging="360"/></w:pPr></w:lvl><w:lvl w:ilvl="7" w:tentative="on"><w:start w:val="1"/><w:nfc w:val="4"/><w:lvlText w:val="%8."/><w:lvlJc w:val="left"/><w:pPr><w:tabs><w:tab w:val="list" w:pos="5760"/></w:tabs><w:ind w:left="5760" w:hanging="360"/></w:pPr></w:lvl><w:lvl w:ilvl="8" w:tentative="on"><w:start w:val="1"/><w:nfc w:val="2"/><w:lvlText w:val="%9."/><w:lvlJc w:val="right"/><w:pPr><w:tabs><w:tab w:val="list" w:pos="6480"/></w:tabs><w:ind w:left="6480" w:hanging="180"/></w:pPr></w:lvl></w:listDef><w:listDef w:listDefId="15"><w:lsid w:val="78A34B7A"/><w:plt w:val="SingleLevel"/><w:tmpl w:val="07B4FABE"/><w:lvl w:ilvl="0"><w:start w:val="1"/><w:nfc w:val="255"/><w:lvlText w:val=""/><w:legacy w:legacy="on" w:legacySpace="0" w:legacyIndent="360"/><w:lvlJc w:val="left"/><w:pPr><w:ind w:left="360" w:hanging="360"/></w:pPr></w:lvl></w:listDef><w:list w:ilfo="1"><w:ilst w:val="5"/></w:list><w:list w:ilfo="2"><w:ilst w:val="4"/></w:list><w:list w:ilfo="3"><w:ilst w:val="3"/></w:list><w:list w:ilfo="4"><w:ilst w:val="2"/></w:list><w:list w:ilfo="5"><w:ilst w:val="1"/></w:list><w:list w:ilfo="6"><w:ilst w:val="0"/></w:list><w:list w:ilfo="7"><w:ilst w:val="9"/></w:list><w:list w:ilfo="8"><w:ilst w:val="12"/></w:list><w:list w:ilfo="9"><w:ilst w:val="8"/></w:list><w:list w:ilfo="10"><w:ilst w:val="14"/></w:list><w:list w:ilfo="11"><w:ilst w:val="11"/></w:list><w:list w:ilfo="12"><w:ilst w:val="13"/></w:list><w:list w:ilfo="13"><w:ilst w:val="15"/></w:list><w:list w:ilfo="14"><w:ilst w:val="10"/></w:list><w:list w:ilfo="15"><w:ilst w:val="6"/></w:list><w:list w:ilfo="16"><w:ilst w:val="7"/></w:list><w:list w:ilfo="17"><w:ilst w:val="2"/></w:list><w:list w:ilfo="18"><w:ilst w:val="7"/></w:list></w:lists><w:styles><w:versionOfBuiltInStylenames w:val="4"/><w:latentStyles w:defLockedState="off" w:latentStyleCount="156"/><w:style w:type="paragraph" w:default="on" w:styleId="Standard"><w:name w:val="Normal"/><wx:uiName wx:val="Standard"/><w:pPr><w:spacing w:before="60" w:after="60"/></w:pPr><w:rPr><wx:font wx:val="Times New Roman"/><w:lang w:val="EN-IE" w:fareast="DE" w:bidi="AR-SA"/></w:rPr></w:style><w:style w:type="paragraph" w:styleId="berschrift1"><w:name w:val="heading 1"/><wx:uiName wx:val="Überschrift 1"/><w:basedOn w:val="Standard"/><w:next w:val="Standard"/><w:pPr><w:pStyle w:val="berschrift1"/><w:keepNext/><w:spacing w:before="240"/><w:outlineLvl w:val="0"/></w:pPr><w:rPr><w:rFonts w:ascii="Arial" w:h-ansi="Arial"/><wx:font wx:val="Arial"/><w:b/><w:sz w:val="32"/><w:lang w:val="EN-US"/></w:rPr></w:style><w:style w:type="paragraph" w:styleId="berschrift2"><w:name w:val="heading 2"/><wx:uiName wx:val="Überschrift 2"/><w:basedOn w:val="Standard"/><w:next w:val="Standard"/><w:pPr><w:pStyle w:val="berschrift2"/><w:keepNext/><w:spacing w:before="240"/><w:outlineLvl w:val="1"/></w:pPr><w:rPr><w:rFonts w:ascii="Arial" w:h-ansi="Arial"/><wx:font wx:val="Arial"/><w:b/><w:i/><w:sz w:val="28"/></w:rPr></w:style><w:style w:type="paragraph" w:styleId="berschrift3"><w:name w:val="heading 3"/><wx:uiName wx:val="Überschrift 3"/><w:basedOn w:val="Standard"/><w:next w:val="Standard"/><w:pPr><w:pStyle w:val="berschrift3"/><w:keepNext/><w:spacing w:before="240"/><w:outlineLvl w:val="2"/></w:pPr><w:rPr><w:rFonts w:ascii="Arial" w:h-ansi="Arial"/><wx:font wx:val="Arial"/><w:sz w:val="28"/></w:rPr></w:style><w:style w:type="paragraph" w:styleId="berschrift4"><w:name w:val="heading 4"/><wx:uiName wx:val="Überschrift 4"/><w:basedOn w:val="Standard"/><w:next w:val="Standard"/><w:pPr><w:pStyle w:val="berschrift4"/><w:keepNext/><w:spacing w:before="240"/><w:outlineLvl w:val="3"/></w:pPr><w:rPr><w:rFonts w:ascii="Arial" w:h-ansi="Arial"/><wx:font wx:val="Arial"/><w:b/><w:sz w:val="24"/></w:rPr></w:style><w:style w:type="paragraph" w:styleId="berschrift5"><w:name w:val="heading 5"/><wx:uiName wx:val="Überschrift 5"/><w:basedOn w:val="Standard"/><w:next w:val="Standard"/><w:pPr><w:pStyle w:val="berschrift5"/><w:spacing w:before="240"/><w:outlineLvl w:val="4"/></w:pPr><w:rPr><w:rFonts w:ascii="Arial" w:h-ansi="Arial"/><wx:font wx:val="Arial"/><w:sz w:val="22"/></w:rPr></w:style><w:style w:type="paragraph" w:styleId="berschrift6"><w:name w:val="heading 6"/><wx:uiName wx:val="Überschrift 6"/><w:basedOn w:val="Standard"/><w:next w:val="Standard"/><w:pPr><w:pStyle w:val="berschrift6"/><w:spacing w:before="240"/><w:outlineLvl w:val="5"/></w:pPr><w:rPr><wx:font wx:val="Times New Roman"/><w:i/><w:sz w:val="22"/></w:rPr></w:style><w:style w:type="character" w:default="on" w:styleId="Absatz-Standardschriftart"><w:name w:val="Default Paragraph Font"/><wx:uiName wx:val="Absatz-Standardschriftart"/><w:semiHidden/></w:style><w:style w:type="table" w:default="on" w:styleId="NormaleTabelle"><w:name w:val="Normal Table"/><wx:uiName wx:val="Normale Tabelle"/><w:semiHidden/><w:rPr><wx:font wx:val="Times New Roman"/></w:rPr><w:tblPr><w:tblInd w:w="0" w:type="dxa"/><w:tblCellMar><w:top w:w="0" w:type="dxa"/><w:left w:w="108" w:type="dxa"/><w:bottom w:w="0" w:type="dxa"/><w:right w:w="108" w:type="dxa"/></w:tblCellMar></w:tblPr></w:style><w:style w:type="list" w:default="on" w:styleId="KeineListe"><w:name w:val="No List"/><wx:uiName wx:val="Keine Liste"/><w:semiHidden/></w:style><w:style w:type="paragraph" w:styleId="Titel"><w:name w:val="Title"/><wx:uiName wx:val="Titel"/><w:basedOn w:val="Standard"/><w:next w:val="Author"/><w:pPr><w:pStyle w:val="Titel"/><w:spacing w:before="240"/><w:jc w:val="center"/></w:pPr><w:rPr><w:rFonts w:ascii="Arial" w:h-ansi="Arial"/><wx:font wx:val="Arial"/><w:b/><w:kern w:val="28"/><w:sz w:val="48"/><w:lang w:val="EN-US"/></w:rPr></w:style><w:style w:type="paragraph" w:styleId="Author"><w:name w:val="Author"/><w:basedOn w:val="Standard"/><w:next w:val="Jobtitle"/><w:pPr><w:pStyle w:val="Author"/></w:pPr><w:rPr><wx:font wx:val="Times New Roman"/><w:i/></w:rPr></w:style><w:style w:type="paragraph" w:styleId="Jobtitle"><w:name w:val="Jobtitle"/><w:basedOn w:val="Standard"/><w:next w:val="Orgname"/><w:autoRedefine/><w:pPr><w:pStyle w:val="Jobtitle"/></w:pPr><w:rPr><w:rFonts w:ascii="Garamond" w:h-ansi="Garamond"/><wx:font wx:val="Garamond"/><w:i/><w:spacing w:val="5"/><w:sz w:val="23"/><w:lang w:val="EN-US"/></w:rPr></w:style><w:style w:type="paragraph" w:styleId="Orgname"><w:name w:val="Orgname"/><w:basedOn w:val="Standard"/><w:next w:val="Keywordset"/><w:pPr><w:pStyle w:val="Orgname"/></w:pPr><w:rPr><wx:font wx:val="Times New Roman"/></w:rPr></w:style><w:style w:type="paragraph" w:styleId="Keywordset"><w:name w:val="Keywordset"/><w:basedOn w:val="Standard"/><w:next w:val="Standard"/><w:autoRedefine/><w:pPr><w:pStyle w:val="Keywordset"/></w:pPr><w:rPr><wx:font wx:val="Times New Roman"/></w:rPr></w:style><w:style w:type="paragraph" w:styleId="TableHead"><w:name w:val="Table Head"/><w:basedOn w:val="Standard"/><w:autoRedefine/><w:pPr><w:pStyle w:val="TableHead"/><w:spacing w:before="240"/><w:ind w:left="283" w:hanging="283"/><w:jc w:val="center"/></w:pPr><w:rPr><w:rFonts w:ascii="Arial" w:h-ansi="Arial"/><wx:font wx:val="Arial"/><w:b/><w:lang w:val="EN-US"/></w:rPr></w:style><w:style w:type="paragraph" w:styleId="Verzeichnis1"><w:name w:val="toc 1"/><wx:uiName wx:val="Verzeichnis 1"/><w:basedOn w:val="Standard"/><w:next w:val="Standard"/><w:semiHidden/><w:pPr><w:pStyle w:val="Verzeichnis1"/><w:tabs><w:tab w:val="right" w:leader="dot" w:pos="8640"/></w:tabs></w:pPr><w:rPr><wx:font wx:val="Times New Roman"/></w:rPr></w:style><w:style w:type="paragraph" w:styleId="Listennummer"><w:name w:val="List Number"/><wx:uiName wx:val="Listennummer"/><w:basedOn w:val="Standard"/><w:pPr><w:pStyle w:val="Listennummer"/><w:ind w:left="360" w:hanging="360"/><w:jc w:val="both"/></w:pPr><w:rPr><wx:font wx:val="Times New Roman"/></w:rPr></w:style><w:style w:type="paragraph" w:styleId="Aufzhlungszeichen"><w:name w:val="List Bullet"/><wx:uiName wx:val="Aufzählungszeichen"/><w:basedOn w:val="Standard"/><w:pPr><w:pStyle w:val="Aufzhlungszeichen"/><w:widowControl w:val="off"/><w:listPr><w:ilfo w:val="14"/></w:listPr></w:pPr><w:rPr><wx:font wx:val="Times New Roman"/><w:sz w:val="24"/><w:lang w:val="EN-US"/></w:rPr></w:style><w:style w:type="character" w:styleId="Funotenzeichen"><w:name w:val="footnote reference"/><wx:uiName wx:val="Fußnotenzeichen"/><w:basedOn w:val="Absatz-Standardschriftart"/><w:semiHidden/><w:rPr><w:vertAlign w:val="superscript"/></w:rPr></w:style><w:style w:type="character" w:styleId="ListTitle"><w:name w:val="ListTitle"/><w:basedOn w:val="Absatz-Standardschriftart"/><w:rPr><w:i/></w:rPr></w:style><w:style w:type="paragraph" w:styleId="Listenfortsetzung5"><w:name w:val="List Continue 5"/><wx:uiName wx:val="Listenfortsetzung 5"/><w:basedOn w:val="Standard"/><w:pPr><w:pStyle w:val="Listenfortsetzung5"/><w:spacing w:after="120"/><w:ind w:left="1800"/></w:pPr><w:rPr><wx:font wx:val="Times New Roman"/></w:rPr></w:style><w:style w:type="paragraph" w:styleId="Listenfortsetzung"><w:name w:val="List Continue"/><wx:uiName wx:val="Listenfortsetzung"/><w:basedOn w:val="Standard"/><w:pPr><w:pStyle w:val="Listenfortsetzung"/><w:spacing w:after="120"/><w:ind w:left="283"/></w:pPr><w:rPr><wx:font wx:val="Times New Roman"/><w:lang w:val="EN-US"/></w:rPr></w:style><w:style w:type="paragraph" w:styleId="Listennummer2"><w:name w:val="List Number 2"/><wx:uiName wx:val="Listennummer 2"/><w:basedOn w:val="Standard"/><w:pPr><w:pStyle w:val="Listennummer2"/><w:ind w:left="720" w:hanging="360"/><w:jc w:val="both"/></w:pPr><w:rPr><wx:font wx:val="Times New Roman"/></w:rPr></w:style><w:style w:type="paragraph" w:styleId="Aufzhlungszeichen2"><w:name w:val="List Bullet 2"/><wx:uiName wx:val="Aufzählungszeichen 2"/><w:basedOn w:val="Standard"/><w:pPr><w:pStyle w:val="Aufzhlungszeichen2"/><w:listPr><w:ilfo w:val="15"/></w:listPr></w:pPr><w:rPr><wx:font wx:val="Times New Roman"/><w:lang w:val="EN-US"/></w:rPr></w:style><w:style w:type="character" w:styleId="Acronym"><w:name w:val="Acronym"/><w:basedOn w:val="Absatz-Standardschriftart"/></w:style><w:style w:type="character" w:styleId="Mailto"><w:name w:val="Mailto"/><w:basedOn w:val="Absatz-Standardschriftart"/><w:rPr><w:rFonts w:ascii="Arial" w:h-ansi="Arial"/><w:b/><w:color w:val="0000FF"/><w:sz w:val="16"/><w:u w:val="single"/></w:rPr></w:style><w:style w:type="paragraph" w:styleId="Textkrper"><w:name w:val="Body Text"/><wx:uiName wx:val="Textkörper"/><w:basedOn w:val="Standard"/><w:pPr><w:pStyle w:val="Textkrper"/><w:spacing w:after="120"/></w:pPr><w:rPr><wx:font wx:val="Times New Roman"/></w:rPr></w:style><w:style w:type="paragraph" w:styleId="Acknowledgement"><w:name w:val="Acknowledgement"/><w:basedOn w:val="Standard"/><w:pPr><w:pStyle w:val="Acknowledgement"/></w:pPr><w:rPr><wx:font wx:val="Times New Roman"/></w:rPr></w:style><w:style w:type="paragraph" w:styleId="Datum"><w:name w:val="Date"/><wx:uiName wx:val="Datum"/><w:basedOn w:val="Standard"/><w:pPr><w:pStyle w:val="Datum"/></w:pPr><w:rPr><wx:font wx:val="Times New Roman"/></w:rPr></w:style><w:style w:type="paragraph" w:styleId="ISBNNumber"><w:name w:val="ISBN Number"/><w:basedOn w:val="Standard"/><w:pPr><w:pStyle w:val="ISBNNumber"/></w:pPr><w:rPr><wx:font wx:val="Times New Roman"/></w:rPr></w:style><w:style w:type="paragraph" w:styleId="TableTitle"><w:name w:val="Table Title"/><w:basedOn w:val="Standard"/><w:pPr><w:pStyle w:val="TableTitle"/><w:keepNext/><w:spacing w:before="240"/><w:jc w:val="center"/></w:pPr><w:rPr><wx:font wx:val="Times New Roman"/></w:rPr></w:style><w:style w:type="character" w:styleId="Attribution"><w:name w:val="Attribution"/><w:basedOn w:val="Absatz-Standardschriftart"/></w:style><w:style w:type="character" w:styleId="Audiodata"><w:name w:val="Audiodata"/><w:basedOn w:val="Absatz-Standardschriftart"/></w:style><w:style w:type="paragraph" w:styleId="Authorinitials"><w:name w:val="Authorinitials"/><w:basedOn w:val="Standard"/><w:next w:val="Standard"/><w:autoRedefine/><w:pPr><w:pStyle w:val="Authorinitials"/></w:pPr><w:rPr><wx:font wx:val="Times New Roman"/></w:rPr></w:style><w:style w:type="character" w:styleId="Bibliomisc"><w:name w:val="Bibliomisc"/><w:basedOn w:val="Absatz-Standardschriftart"/></w:style><w:style w:type="character" w:styleId="CiteTitle"><w:name w:val="CiteTitle"/><w:basedOn w:val="Absatz-Standardschriftart"/></w:style><w:style w:type="character" w:styleId="Command"><w:name w:val="Command"/><w:basedOn w:val="Absatz-Standardschriftart"/></w:style><w:style w:type="character" w:styleId="Computeroutput"><w:name w:val="Computeroutput"/><w:basedOn w:val="Absatz-Standardschriftart"/></w:style><w:style w:type="character" w:styleId="Filename"><w:name w:val="Filename"/><w:basedOn w:val="Absatz-Standardschriftart"/></w:style><w:style w:type="character" w:styleId="Firstname"><w:name w:val="Firstname"/><w:basedOn w:val="Absatz-Standardschriftart"/></w:style><w:style w:type="character" w:styleId="Honorific"><w:name w:val="Honorific"/><w:basedOn w:val="Absatz-Standardschriftart"/></w:style><w:style w:type="character" w:styleId="Imagedata"><w:name w:val="Imagedata"/><w:basedOn w:val="Absatz-Standardschriftart"/></w:style><w:style w:type="character" w:styleId="Keyword"><w:name w:val="Keyword"/><w:basedOn w:val="Absatz-Standardschriftart"/></w:style><w:style w:type="character" w:styleId="Lineannotation"><w:name w:val="Lineannotation"/><w:basedOn w:val="Absatz-Standardschriftart"/></w:style><w:style w:type="character" w:styleId="Link"><w:name w:val="Link"/><w:basedOn w:val="Absatz-Standardschriftart"/></w:style><w:style w:type="character" w:styleId="Literal"><w:name w:val="Literal"/><w:basedOn w:val="Absatz-Standardschriftart"/></w:style><w:style w:type="paragraph" w:styleId="Programlisting"><w:name w:val="Programlisting"/><w:basedOn w:val="Standard"/><w:next w:val="Standard"/><w:autoRedefine/><w:pPr><w:pStyle w:val="Programlisting"/></w:pPr><w:rPr><wx:font wx:val="Times New Roman"/></w:rPr></w:style><w:style w:type="character" w:styleId="Literallayout"><w:name w:val="Literallayout"/><w:basedOn w:val="Absatz-Standardschriftart"/></w:style><w:style w:type="character" w:styleId="Phrase"><w:name w:val="Phrase"/><w:basedOn w:val="Absatz-Standardschriftart"/></w:style><w:style w:type="character" w:styleId="Replaceable"><w:name w:val="Replaceable"/><w:basedOn w:val="Absatz-Standardschriftart"/></w:style><w:style w:type="character" w:styleId="Subjectterm"><w:name w:val="Subjectterm"/><w:basedOn w:val="Absatz-Standardschriftart"/></w:style><w:style w:type="paragraph" w:styleId="Videolink"><w:name w:val="Videolink"/><w:basedOn w:val="Standard"/><w:next w:val="Standard"/><w:autoRedefine/><w:pPr><w:pStyle w:val="Videolink"/></w:pPr><w:rPr><wx:font wx:val="Times New Roman"/></w:rPr></w:style><w:style w:type="paragraph" w:styleId="Term"><w:name w:val="Term"/><w:basedOn w:val="Standard"/><w:next w:val="Standard"/><w:autoRedefine/><w:pPr><w:pStyle w:val="Term"/></w:pPr><w:rPr><wx:font wx:val="Times New Roman"/></w:rPr></w:style><w:style w:type="paragraph" w:styleId="Xlink"><w:name w:val="Xlink"/><w:basedOn w:val="Standard"/><w:next w:val="Standard"/><w:autoRedefine/><w:pPr><w:pStyle w:val="Xlink"/></w:pPr><w:rPr><wx:font wx:val="Times New Roman"/></w:rPr></w:style><w:style w:type="character" w:styleId="Trademark"><w:name w:val="Trademark"/><w:basedOn w:val="Absatz-Standardschriftart"/></w:style><w:style w:type="character" w:styleId="Quote"><w:name w:val="Quote"/><w:basedOn w:val="Absatz-Standardschriftart"/></w:style><w:style w:type="paragraph" w:styleId="Abstract"><w:name w:val="Abstract"/><w:basedOn w:val="Standard"/><w:next w:val="Author"/><w:autoRedefine/><w:pPr><w:pStyle w:val="Abstract"/><w:spacing w:before="120" w:after="120"/><w:jc w:val="center"/></w:pPr><w:rPr><wx:font wx:val="Times New Roman"/><w:i/><w:color w:val="0000FF"/></w:rPr></w:style><w:style w:type="paragraph" w:styleId="Appendix"><w:name w:val="Appendix"/><w:basedOn w:val="Standard"/><w:next w:val="Standard"/><w:autoRedefine/><w:pPr><w:pStyle w:val="Appendix"/></w:pPr><w:rPr><wx:font wx:val="Times New Roman"/></w:rPr></w:style><w:style w:type="paragraph" w:styleId="Audioobject"><w:name w:val="Audioobject"/><w:basedOn w:val="Standard"/><w:next w:val="Standard"/><w:autoRedefine/><w:pPr><w:pStyle w:val="Audioobject"/></w:pPr><w:rPr><wx:font wx:val="Times New Roman"/></w:rPr></w:style><w:style w:type="paragraph" w:styleId="Authorblurb"><w:name w:val="Authorblurb"/><w:basedOn w:val="Standard"/><w:next w:val="Standard"/><w:autoRedefine/><w:pPr><w:pStyle w:val="Authorblurb"/></w:pPr><w:rPr><wx:font wx:val="Times New Roman"/></w:rPr></w:style><w:style w:type="paragraph" w:styleId="Authorgroup"><w:name w:val="Authorgroup"/><w:basedOn w:val="Standard"/><w:next w:val="Standard"/><w:autoRedefine/><w:pPr><w:pStyle w:val="Authorgroup"/></w:pPr><w:rPr><wx:font wx:val="Times New Roman"/></w:rPr></w:style><w:style w:type="character" w:styleId="Userinput"><w:name w:val="Userinput"/><w:basedOn w:val="Absatz-Standardschriftart"/></w:style><w:style w:type="paragraph" w:styleId="Bibliodiv"><w:name w:val="Bibliodiv"/><w:basedOn w:val="Standard"/><w:next w:val="Standard"/><w:autoRedefine/><w:pPr><w:pStyle w:val="Bibliodiv"/></w:pPr><w:rPr><wx:font wx:val="Times New Roman"/></w:rPr></w:style><w:style w:type="paragraph" w:styleId="Bibliography"><w:name w:val="Bibliography"/><w:basedOn w:val="Standard"/><w:next w:val="Standard"/><w:autoRedefine/><w:pPr><w:pStyle w:val="Bibliography"/></w:pPr><w:rPr><wx:font wx:val="Times New Roman"/></w:rPr></w:style><w:style w:type="paragraph" w:styleId="Bibliomixed"><w:name w:val="Bibliomixed"/><w:basedOn w:val="Standard"/><w:next w:val="Standard"/><w:autoRedefine/><w:pPr><w:pStyle w:val="Bibliomixed"/></w:pPr><w:rPr><wx:font wx:val="Times New Roman"/></w:rPr></w:style><w:style w:type="paragraph" w:styleId="Bibliomset"><w:name w:val="Bibliomset"/><w:basedOn w:val="Standard"/><w:next w:val="Standard"/><w:autoRedefine/><w:pPr><w:pStyle w:val="Bibliomset"/></w:pPr><w:rPr><wx:font wx:val="Times New Roman"/></w:rPr></w:style><w:style w:type="paragraph" w:styleId="Blockquote"><w:name w:val="Blockquote"/><w:basedOn w:val="Standard"/><w:next w:val="Standard"/><w:autoRedefine/><w:pPr><w:pStyle w:val="Blockquote"/></w:pPr><w:rPr><wx:font wx:val="Times New Roman"/></w:rPr></w:style><w:style w:type="character" w:styleId="Videodata"><w:name w:val="Videodata"/><w:basedOn w:val="Absatz-Standardschriftart"/></w:style><w:style w:type="paragraph" w:styleId="Copyright"><w:name w:val="Copyright"/><w:basedOn w:val="Standard"/><w:next w:val="Standard"/><w:autoRedefine/><w:pPr><w:pStyle w:val="Copyright"/></w:pPr><w:rPr><wx:font wx:val="Times New Roman"/></w:rPr></w:style><w:style w:type="paragraph" w:styleId="Corpauthor"><w:name w:val="Corpauthor"/><w:basedOn w:val="Standard"/><w:next w:val="Standard"/><w:autoRedefine/><w:pPr><w:pStyle w:val="Corpauthor"/></w:pPr><w:rPr><wx:font wx:val="Times New Roman"/></w:rPr></w:style><w:style w:type="paragraph" w:styleId="Edition"><w:name w:val="Edition"/><w:basedOn w:val="Standard"/><w:next w:val="Standard"/><w:autoRedefine/><w:pPr><w:pStyle w:val="Edition"/></w:pPr><w:rPr><wx:font wx:val="Times New Roman"/></w:rPr></w:style><w:style w:type="paragraph" w:styleId="Editor"><w:name w:val="Editor"/><w:basedOn w:val="Standard"/><w:next w:val="Standard"/><w:autoRedefine/><w:pPr><w:pStyle w:val="Editor"/></w:pPr><w:rPr><wx:font wx:val="Times New Roman"/></w:rPr></w:style><w:style w:type="paragraph" w:styleId="Epigraph"><w:name w:val="Epigraph"/><w:basedOn w:val="Standard"/><w:next w:val="Standard"/><w:autoRedefine/><w:pPr><w:pStyle w:val="Epigraph"/></w:pPr><w:rPr><wx:font wx:val="Times New Roman"/></w:rPr></w:style><w:style w:type="paragraph" w:styleId="Example"><w:name w:val="Example"/><w:basedOn w:val="Standard"/><w:next w:val="Standard"/><w:autoRedefine/><w:pPr><w:pStyle w:val="Example"/></w:pPr><w:rPr><wx:font wx:val="Times New Roman"/></w:rPr></w:style><w:style w:type="paragraph" w:styleId="Figure"><w:name w:val="Figure"/><w:basedOn w:val="Standard"/><w:next w:val="Standard"/><w:autoRedefine/><w:pPr><w:pStyle w:val="Figure"/></w:pPr><w:rPr><wx:font wx:val="Times New Roman"/></w:rPr></w:style><w:style w:type="character" w:styleId="Xref"><w:name w:val="Xref"/><w:basedOn w:val="Absatz-Standardschriftart"/></w:style><w:style w:type="paragraph" w:styleId="Holder"><w:name w:val="Holder"/><w:basedOn w:val="Standard"/><w:next w:val="Standard"/><w:autoRedefine/><w:pPr><w:pStyle w:val="Holder"/></w:pPr><w:rPr><wx:font wx:val="Times New Roman"/></w:rPr></w:style><w:style w:type="paragraph" w:styleId="Imageobject"><w:name w:val="Imageobject"/><w:basedOn w:val="Standard"/><w:next w:val="Standard"/><w:autoRedefine/><w:pPr><w:pStyle w:val="Imageobject"/></w:pPr><w:rPr><wx:font wx:val="Times New Roman"/></w:rPr></w:style><w:style w:type="character" w:styleId="Inlinemediaobject"><w:name w:val="Inlinemediaobject"/><w:basedOn w:val="Absatz-Standardschriftart"/></w:style><w:style w:type="paragraph" w:styleId="Issuenum"><w:name w:val="Issuenum"/><w:basedOn w:val="Standard"/><w:next w:val="Standard"/><w:autoRedefine/><w:pPr><w:pStyle w:val="Issuenum"/></w:pPr><w:rPr><wx:font wx:val="Times New Roman"/></w:rPr></w:style><w:style w:type="paragraph" w:styleId="Legalnotice"><w:name w:val="Legalnotice"/><w:basedOn w:val="Standard"/><w:next w:val="Standard"/><w:autoRedefine/><w:pPr><w:pStyle w:val="Legalnotice"/></w:pPr><w:rPr><wx:font wx:val="Times New Roman"/></w:rPr></w:style><w:style w:type="character" w:styleId="Lineage"><w:name w:val="Lineage"/><w:basedOn w:val="Absatz-Standardschriftart"/></w:style><w:style w:type="paragraph" w:styleId="Mediaobject"><w:name w:val="Mediaobject"/><w:basedOn w:val="Standard"/><w:next w:val="Standard"/><w:autoRedefine/><w:pPr><w:pStyle w:val="Mediaobject"/></w:pPr><w:rPr><wx:font wx:val="Times New Roman"/></w:rPr></w:style><w:style w:type="paragraph" w:styleId="Note"><w:name w:val="Note"/><w:basedOn w:val="Standard"/><w:next w:val="Standard"/><w:autoRedefine/><w:pPr><w:pStyle w:val="Note"/></w:pPr><w:rPr><wx:font wx:val="Times New Roman"/></w:rPr></w:style><w:style w:type="character" w:styleId="Option"><w:name w:val="Option"/><w:basedOn w:val="Absatz-Standardschriftart"/></w:style><w:style w:type="paragraph" w:styleId="Othercredit"><w:name w:val="Othercredit"/><w:basedOn w:val="Standard"/><w:next w:val="Standard"/><w:autoRedefine/><w:pPr><w:pStyle w:val="Othercredit"/></w:pPr><w:rPr><wx:font wx:val="Times New Roman"/></w:rPr></w:style><w:style w:type="character" w:styleId="Othername"><w:name w:val="Othername"/><w:basedOn w:val="Absatz-Standardschriftart"/></w:style><w:style w:type="character" w:styleId="Pubdate"><w:name w:val="Pubdate"/><w:basedOn w:val="Absatz-Standardschriftart"/></w:style><w:style w:type="paragraph" w:styleId="Publishername"><w:name w:val="Publishername"/><w:basedOn w:val="Standard"/><w:next w:val="Standard"/><w:autoRedefine/><w:pPr><w:pStyle w:val="Publishername"/></w:pPr><w:rPr><wx:font wx:val="Times New Roman"/></w:rPr></w:style><w:style w:type="paragraph" w:styleId="Releaseinfo"><w:name w:val="Releaseinfo"/><w:basedOn w:val="Standard"/><w:next w:val="Standard"/><w:autoRedefine/><w:pPr><w:pStyle w:val="Releaseinfo"/></w:pPr><w:rPr><wx:font wx:val="Times New Roman"/></w:rPr></w:style><w:style w:type="paragraph" w:styleId="Revdescription"><w:name w:val="Revdescription"/><w:basedOn w:val="Standard"/><w:next w:val="Standard"/><w:autoRedefine/><w:pPr><w:pStyle w:val="Revdescription"/></w:pPr><w:rPr><wx:font wx:val="Times New Roman"/></w:rPr></w:style><w:style w:type="paragraph" w:styleId="Revhistory"><w:name w:val="Revhistory"/><w:basedOn w:val="Standard"/><w:next w:val="Standard"/><w:autoRedefine/><w:pPr><w:pStyle w:val="Revhistory"/></w:pPr><w:rPr><wx:font wx:val="Times New Roman"/></w:rPr></w:style><w:style w:type="paragraph" w:styleId="Revision"><w:name w:val="Revision"/><w:basedOn w:val="Standard"/><w:next w:val="Standard"/><w:autoRedefine/><w:pPr><w:pStyle w:val="Revision"/></w:pPr><w:rPr><wx:font wx:val="Times New Roman"/></w:rPr></w:style><w:style w:type="character" w:styleId="Revnumber"><w:name w:val="Revnumber"/><w:basedOn w:val="Absatz-Standardschriftart"/></w:style><w:style w:type="paragraph" w:styleId="Revremark"><w:name w:val="Revremark"/><w:basedOn w:val="Standard"/><w:next w:val="Standard"/><w:autoRedefine/><w:pPr><w:pStyle w:val="Revremark"/></w:pPr><w:rPr><wx:font wx:val="Times New Roman"/></w:rPr></w:style><w:style w:type="paragraph" w:styleId="Sectioninfo"><w:name w:val="Sectioninfo"/><w:basedOn w:val="Standard"/><w:next w:val="Standard"/><w:autoRedefine/><w:pPr><w:pStyle w:val="Sectioninfo"/></w:pPr><w:rPr><wx:font wx:val="Times New Roman"/></w:rPr></w:style><w:style w:type="paragraph" w:styleId="Sidebar"><w:name w:val="Sidebar"/><w:basedOn w:val="Standard"/><w:next w:val="Standard"/><w:autoRedefine/><w:pPr><w:pStyle w:val="Sidebar"/></w:pPr><w:rPr><wx:font wx:val="Times New Roman"/></w:rPr></w:style><w:style w:type="paragraph" w:styleId="Subject"><w:name w:val="Subject"/><w:basedOn w:val="Standard"/><w:next w:val="Standard"/><w:autoRedefine/><w:pPr><w:pStyle w:val="Subject"/></w:pPr><w:rPr><wx:font wx:val="Times New Roman"/></w:rPr></w:style><w:style w:type="paragraph" w:styleId="Subjectset"><w:name w:val="Subjectset"/><w:basedOn w:val="Standard"/><w:next w:val="Standard"/><w:autoRedefine/><w:pPr><w:pStyle w:val="Subjectset"/></w:pPr><w:rPr><wx:font wx:val="Times New Roman"/></w:rPr></w:style><w:style w:type="character" w:styleId="Surname"><w:name w:val="Surname"/><w:basedOn w:val="Absatz-Standardschriftart"/></w:style><w:style w:type="character" w:styleId="Systemitem"><w:name w:val="Systemitem"/><w:basedOn w:val="Absatz-Standardschriftart"/></w:style><w:style w:type="paragraph" w:styleId="Textobject"><w:name w:val="Textobject"/><w:basedOn w:val="Standard"/><w:next w:val="Standard"/><w:autoRedefine/><w:pPr><w:pStyle w:val="Textobject"/></w:pPr><w:rPr><wx:font wx:val="Times New Roman"/></w:rPr></w:style><w:style w:type="paragraph" w:styleId="Variablelist"><w:name w:val="Variablelist"/><w:basedOn w:val="Standard"/><w:next w:val="Standard"/><w:autoRedefine/><w:pPr><w:pStyle w:val="Variablelist"/></w:pPr><w:rPr><wx:font wx:val="Times New Roman"/></w:rPr></w:style><w:style w:type="paragraph" w:styleId="Varlistentry"><w:name w:val="Varlistentry"/><w:basedOn w:val="Standard"/><w:next w:val="Standard"/><w:autoRedefine/><w:pPr><w:pStyle w:val="Varlistentry"/></w:pPr><w:rPr><wx:font wx:val="Times New Roman"/></w:rPr></w:style><w:style w:type="paragraph" w:styleId="Videoobject"><w:name w:val="Videoobject"/><w:basedOn w:val="Standard"/><w:next w:val="Standard"/><w:autoRedefine/><w:pPr><w:pStyle w:val="Videoobject"/></w:pPr><w:rPr><wx:font wx:val="Times New Roman"/></w:rPr></w:style><w:style w:type="character" w:styleId="Volumenum"><w:name w:val="Volumenum"/><w:basedOn w:val="Absatz-Standardschriftart"/></w:style><w:style w:type="character" w:styleId="Year"><w:name w:val="Year"/><w:basedOn w:val="Absatz-Standardschriftart"/></w:style><w:style w:type="character" w:styleId="Abbreviation"><w:name w:val="Abbreviation"/><w:basedOn w:val="Absatz-Standardschriftart"/></w:style><w:style w:type="paragraph" w:styleId="Liste"><w:name w:val="List"/><wx:uiName wx:val="Liste"/><w:basedOn w:val="Standard"/><w:pPr><w:pStyle w:val="Liste"/><w:ind w:left="360" w:hanging="360"/><w:jc w:val="both"/></w:pPr><w:rPr><wx:font wx:val="Times New Roman"/></w:rPr></w:style><w:style w:type="paragraph" w:styleId="Liste2"><w:name w:val="List 2"/><wx:uiName wx:val="Liste 2"/><w:basedOn w:val="Standard"/><w:pPr><w:pStyle w:val="Liste2"/><w:ind w:left="720" w:hanging="360"/><w:jc w:val="both"/></w:pPr><w:rPr><wx:font wx:val="Times New Roman"/></w:rPr></w:style><w:style w:type="paragraph" w:styleId="Liste3"><w:name w:val="List 3"/><wx:uiName wx:val="Liste 3"/><w:basedOn w:val="Standard"/><w:pPr><w:pStyle w:val="Liste3"/><w:ind w:left="1080" w:hanging="360"/><w:jc w:val="both"/></w:pPr><w:rPr><wx:font wx:val="Times New Roman"/></w:rPr></w:style><w:style w:type="paragraph" w:styleId="Aufzhlungszeichen3"><w:name w:val="List Bullet 3"/><wx:uiName wx:val="Aufzählungszeichen 3"/><w:basedOn w:val="Standard"/><w:autoRedefine/><w:pPr><w:pStyle w:val="Aufzhlungszeichen3"/><w:listPr><w:ilfo w:val="18"/></w:listPr><w:tabs><w:tab w:val="left" w:pos="576"/></w:tabs></w:pPr><w:rPr><wx:font wx:val="Times New Roman"/><w:lang w:val="EN-US"/></w:rPr></w:style><w:style w:type="paragraph" w:styleId="Listenfortsetzung2"><w:name w:val="List Continue 2"/><wx:uiName wx:val="Listenfortsetzung 2"/><w:basedOn w:val="Standard"/><w:pPr><w:pStyle w:val="Listenfortsetzung2"/><w:spacing w:after="120"/><w:ind w:left="566"/></w:pPr><w:rPr><wx:font wx:val="Times New Roman"/><w:lang w:val="EN-US"/></w:rPr></w:style><w:style w:type="paragraph" w:styleId="Listenfortsetzung3"><w:name w:val="List Continue 3"/><wx:uiName wx:val="Listenfortsetzung 3"/><w:basedOn w:val="Standard"/><w:pPr><w:pStyle w:val="Listenfortsetzung3"/><w:spacing w:after="120"/><w:ind w:left="849"/></w:pPr><w:rPr><wx:font wx:val="Times New Roman"/><w:lang w:val="EN-US"/></w:rPr></w:style><w:style w:type="paragraph" w:styleId="Listennummer3"><w:name w:val="List Number 3"/><wx:uiName wx:val="Listennummer 3"/><w:basedOn w:val="Standard"/><w:pPr><w:pStyle w:val="Listennummer3"/><w:listPr><w:ilfo w:val="17"/></w:listPr><w:tabs><w:tab w:val="clear" w:pos="926"/><w:tab w:val="list" w:pos="1080"/></w:tabs><w:ind w:left="1080"/><w:jc w:val="both"/></w:pPr><w:rPr><wx:font wx:val="Times New Roman"/></w:rPr></w:style></w:styles><w:shapeDefaults><o:shapedefaults v:ext="edit" spidmax="2050"/><o:shapelayout v:ext="edit"><o:idmap v:ext="edit" data="1"/></o:shapelayout></w:shapeDefaults><w:docPr><w:view w:val="normal"/><w:zoom w:percent="100"/><w:doNotEmbedSystemFonts/><w:proofState w:grammar="clean"/><w:attachedTemplate w:val="P:\Programme\Yawc\DocBook\DOCBOOK-en.DOT"/><w:linkStyles/><w:defaultTabStop w:val="720"/><w:displayHorizontalDrawingGridEvery w:val="0"/><w:displayVerticalDrawingGridEvery w:val="0"/><w:useMarginsForDrawingGridOrigin/><w:characterSpacingControl w:val="DontCompress"/><w:optimizeForBrowser/><w:validateAgainstSchema/><w:saveInvalidXML w:val="off"/><w:ignoreMixedContent w:val="off"/><w:alwaysShowPlaceholderText w:val="off"/><w:compat><w:ww6BorderRules/><w:footnoteLayoutLikeWW8/><w:shapeLayoutLikeWW8/><w:alignTablesRowByRow/><w:forgetLastTabAlignment/><w:doNotUseHTMLParagraphAutoSpacing/><w:layoutRawTableWidth/><w:layoutTableRowsApart/><w:useWord97LineBreakingRules/><w:dontAllowFieldEndSelect/><w:useWord2002TableStyleRules/></w:compat></w:docPr><w:body><wx:sect><w:p><w:pPr><w:pStyle w:val="Titel"/></w:pPr><w:r><w:t>Simplified DocBook Article Title</w:t></w:r></w:p><w:p><w:pPr><w:pStyle w:val="Author"/></w:pPr><w:r><w:rPr><w:rStyle w:val="Firstname"/></w:rPr><w:t>Firstname</w:t></w:r><w:r><w:t> </w:t></w:r><w:r><w:rPr><w:rStyle w:val="Surname"/></w:rPr><w:t>Surname</w:t></w:r></w:p><w:p><w:pPr><w:pStyle w:val="Jobtitle"/></w:pPr><w:r><w:t>Job Title - optional</w:t></w:r></w:p><w:p><w:pPr><w:pStyle w:val="Orgname"/></w:pPr><w:r><w:t>Organisation name - optional</w:t></w:r></w:p><w:p><w:pPr><w:pStyle w:val="Keywordset"/><w:rPr><w:rStyle w:val="Keyword"/></w:rPr></w:pPr><w:r><w:rPr><w:rStyle w:val="Keyword"/></w:rPr><w:t>Keyword1</w:t></w:r><w:r><w:t> </w:t></w:r><w:r><w:rPr><w:rStyle w:val="Keyword"/></w:rPr><w:t>Keyword2</w:t></w:r><w:r><w:t> </w:t></w:r><w:r><w:rPr><w:rStyle w:val="Keyword"/></w:rPr><w:t>Keyword3</w:t></w:r></w:p><w:p><w:pPr><w:pStyle w:val="Abstract"/></w:pPr><w:r><w:t>Article Abstract – Optional</w:t></w:r></w:p><w:p><w:r><w:t>This is a paragraph of text</w:t></w:r></w:p><wx:sub-section><w:p><w:pPr><w:pStyle w:val="berschrift1"/></w:pPr><w:r><w:t>Heading level 1</w:t></w:r></w:p><w:p/><w:sectPr><w:pgSz w:w="12240" w:h="15840"/><w:pgMar w:top="1440" w:right="1800" w:bottom="1440" w:left="1800" w:header="720" w:footer="720" w:gutter="0"/><w:cols w:space="720"/></w:sectPr></wx:sub-section></wx:sect></w:body></w:wordDocument>